fastapi_router_viz/__init__.py
fastapi_router_viz/cli.py
fastapi_router_viz/filter.py
fastapi_router_viz/graph.py
fastapi_router_viz/module.py
fastapi_router_viz/server.py
fastapi_router_viz/type.py
fastapi_router_viz/type_helper.py
fastapi_router_viz/version.py
fastapi_router_viz/web/graph-ui.js
fastapi_router_viz/web/graphviz.svg.css
fastapi_router_viz/web/graphviz.svg.js
fastapi_router_viz/web/index.html
fastapi_router_viz/web/quasar.min.css
fastapi_router_viz/web/quasar.min.js
fastapi_router_viz/web/vue-main.js
fastapi_router_viz/web/component/route-code-display.js
fastapi_router_viz/web/component/schema-code-display.js
fastapi_router_viz/web/component/schema-field-filter.js
fastapi_router_viz-0.4.1.dist-info/METADATA
fastapi_router_viz-0.4.1.dist-info/WHEEL
fastapi_router_viz-0.4.1.dist-info/entry_points.txt
fastapi_router_viz-0.4.1.dist-info/licenses/LICENSE
fastapi_router_viz-0.4.1.dist-info/RECORD
