Metadata-Version: 2.4
Name: fastapi-router-viz
Version: 0.4.1
Summary: Visualize FastAPI application's routing tree and dependencies
Project-URL: Homepage, https://github.com/allmonday/fastapi-router-viz
Project-URL: Source, https://github.com/allmonday/fastapi-router-viz
Author-email: Tangkikodo <allmonday@126.com>
License: MIT
License-File: LICENSE
Keywords: fastapi,openapi,routing,visualization
Classifier: Framework :: FastAPI
Classifier: Intended Audience :: Developers
Classifier: License :: OSI Approved :: MIT License
Classifier: Programming Language :: Python :: 3
Classifier: Programming Language :: Python :: 3.9
Classifier: Programming Language :: Python :: 3.10
Classifier: Programming Language :: Python :: 3.11
Classifier: Programming Language :: Python :: 3.12
Requires-Python: >=3.10
Requires-Dist: fastapi>=0.110
Requires-Dist: pydantic-resolve>=1.13.2
Provides-Extra: dev
Requires-Dist: pytest; extra == 'dev'
Requires-Dist: ruff; extra == 'dev'
Requires-Dist: uvicorn; extra == 'dev'
